pve_cloud/_version.py
pve_cloud/cli/pvcli.py
pve_cloud/cli/pvclu.py
pve_cloud/lib/inventory.py
pve_cloud/lib/validate.py
pve_cloud/orm/alchemy.py
pve_cloud/orm/alembic.ini
pve_cloud/orm/migrations/env.py
pve_cloud/orm/migrations/versions/04398db10434_external_cp_extra_sans.py
pve_cloud/orm/migrations/versions/0ad803c51325_machine_type_refactor.py
pve_cloud/orm/migrations/versions/24a548bfce3e_len_rules_enforcements.py
pve_cloud/orm/migrations/versions/27724e407e2b_proxy_fqdn.py
pve_cloud/orm/migrations/versions/3c95509a5de9_fix.py
pve_cloud/orm/migrations/versions/7868bcd05006_migrate_old.py
pve_cloud/orm/migrations/versions/7dea8c4ee39f_init.py
pve_cloud/orm/migrations/versions/944a8fd5d5bc_ext_ctrl_plns.py
pve_cloud/orm/migrations/versions/9de11ef8ba39_vm_vars_and_cloud_secrets.py
pve_cloud/orm/migrations/versions/d9b711555be8_ext_control_plane.py
pve_cloud/orm/migrations/versions/e60b9cc63413_ingress_generic.py
pve_cloud/orm/migrations/versions/e6ae1e138c1f_change_scope_cloud.py
pve_cloud/orm/migrations/versions/ee4924ac4f60_secrets_plural_type.py
pve_cloud/orm/migrations/versions/fdcb5aa33b76_slop_firewall_seperation.py
py_pve_cloud-0.15.5.dist-info/licenses/LICENSE.md
py_pve_cloud-0.15.5.dist-info/METADATA
py_pve_cloud-0.15.5.dist-info/WHEEL
py_pve_cloud-0.15.5.dist-info/entry_points.txt
py_pve_cloud-0.15.5.dist-info/top_level.txt
py_pve_cloud-0.15.5.dist-info/RECORD
