Metadata-Version: 2.4
Name: py-pve-cloud
Version: 0.15.5
Author-email: Tobias Huebner <tobias.huebner@vmzberlin.com>
License-Expression: GPL-3.0-or-later
License-File: LICENSE.md
Requires-Dist: PyYAML==6.0.3
Requires-Dist: psycopg2-binary==2.9.11
Requires-Dist: SQLAlchemy==2.0.45
Requires-Dist: alembic==1.18.0
Requires-Dist: paramiko==4.0.0
Requires-Dist: proxmoxer==2.2.0
Requires-Dist: dnspython==2.8.0
Dynamic: license-file
